flashboot_odbc/__init__.py
flashboot_odbc/database/__init__.py
flashboot_odbc/database/base.py
flashboot_odbc/database/mysql.py
flashboot_odbc/types/__init__.py
py_flashboot_odbc-0.1.0.dist-info/METADATA
py_flashboot_odbc-0.1.0.dist-info/WHEEL
py_flashboot_odbc-0.1.0.dist-info/top_level.txt
py_flashboot_odbc-0.1.0.dist-info/RECORD
