Metadata-Version: 2.4
Name: py-flashboot-odbc
Version: 0.1.0
Summary: Add your description here
Requires-Python: >=3.10
Requires-Dist: flashboot-core>=0.1.19
Requires-Dist: loguru>=0.7.3
Requires-Dist: peewee>=3.18.1
Requires-Dist: pymysql>=1.1.1
